labs/01_tables/bin2bcd.v
module bin2bcd ( 
  input [7:0] bin,
  output reg [9:0] bcd);

  integer i;

  always @(bin) begin
    bcd = 0;
    for(i = 7; i >= 0; i = i-1)
    begin
       if (bcd[7:4] > 4)
          bcd[7:4] = bcd[7:4] + 3;
       if (bcd[3:0] > 4)
          bcd[3:0] = bcd[3:0] + 3;   
       bcd = {bcd,bin[i]};
    end
  end
endmodule

labs/01_tables/tabuada_b.v
module tabuada_b ( //comportamental
  input clk, load, 
  input [7:0] i_a,
  output reg [7:0] res, //resultado
  output reg done); //pronto

  reg [7:0] a_reg;

  integer counter = 0; // Deve ir de 0 a 10
  always @(posedge clk) begin
    if (load) begin
      counter <= 0; // Zera quando estiver no modo carregando(load)
      res <= 8'b00000000; // Deve zerar a saída
      a_reg <= i_a; // Zera o registrador
      done <= 0;
    end else begin
      if (counter < 10) begin
        counter <= counter + 1; // Incrementa
        res <= res + a_reg;
      end else begin
        done <= 1;
      end
    end
  end   
endmodule

labs/01_tables/sim/top_tb.v
// top_tb.v — Testbench Lab 01: Tabuada
`timescale 1ns/1ps

module top_tb;

  reg        clk, load;
  reg  [7:0] i_a;
  wire [7:0] res;
  wire       done;
  wire [9:0] bcd;

  tabuada_b uut (
    .clk(clk), .load(load),
    .i_a(i_a), .res(res), .done(done)
  );

  bin2bcd conv (
    .bin(res), .bcd(bcd)
  );

  initial clk = 0;
  always #5 clk = ~clk;

  initial begin
    $dumpfile("01_tables/sim/dump.vcd");
    $dumpvars(0, top_tb);
  end

  initial begin
    load = 0;
    i_a  = 8'd7; // tabuada do 7

    // pulsa load por 1 ciclo para carregar i_a
    @(posedge clk); #1;
    load = 1;
    @(posedge clk); #1;
    load = 0;

    // aguarda os 10 resultados + 1 ciclo extra
    repeat(12) @(posedge clk);
    $finish;
  end

  // exibe resultado a cada ciclo quando não está em load
  always @(posedge clk) begin
    if (!load)
      $display("t=%0t | %0d x %0d = %0d%0d (done=%b)",
               $time, i_a, uut.counter,
               bcd[7:4], bcd[3:0], done);
  end

endmodule

labs/01_tables/sim/dump.vcd
$date
	Tue Jun  9 00:45:12 2026
$end
$version
	Icarus Verilog
$end
$timescale
	1ps
$end
$scope module top_tb $end
$var wire 8 ! res [7:0] $end
$var wire 1 " done $end
$var wire 10 # bcd [9:0] $end
$var reg 1 $ clk $end
$var reg 8 % i_a [7:0] $end
$var reg 1 & load $end
$scope module conv $end
$var wire 8 ' bin [7:0] $end
$var reg 10 ( bcd [9:0] $end
$var integer 32 ) i [31:0] $end
$upscope $end
$scope module uut $end
$var wire 1 $ clk $end
$var wire 8 * i_a [7:0] $end
$var wire 1 & load $end
$var reg 8 + a_reg [7:0] $end
$var reg 1 " done $end
$var reg 8 , res [7:0] $end
$var integer 32 - counter [31:0] $end
$upscope $end
$upscope $end
$enddefinitions $end
$comment Show the parameter values. $end
$dumpall
$end
#0
$dumpvars
b0 -
bx ,
bx +
b111 *
bx )
bx (
bx '
0&
b111 %
0$
bx #
x"
bx !
$end
#5000
b1 -
1$
#6000
1&
#10000
0$
#15000
b11111111111111111111111111111111 )
b0 #
b0 (
0"
b111 +
b0 !
b0 '
b0 ,
b0 -
1$
#16000
0&
#20000
0$
#25000
b111 #
b111 (
b11111111111111111111111111111111 )
b111 !
b111 '
b111 ,
b1 -
1$
#30000
0$
#35000
b11111111111111111111111111111111 )
b10100 #
b10100 (
b1110 !
b1110 '
b1110 ,
b10 -
1$
#40000
0$
#45000
b11111111111111111111111111111111 )
b100001 #
b100001 (
b10101 !
b10101 '
b10101 ,
b11 -
1$
#50000
0$
#55000
b11111111111111111111111111111111 )
b101000 #
b101000 (
b11100 !
b11100 '
b11100 ,
b100 -
1$
#60000
0$
#65000
b11111111111111111111111111111111 )
b110101 #
b110101 (
b100011 !
b100011 '
b100011 ,
b101 -
1$
#70000
0$
#75000
b11111111111111111111111111111111 )
b1000010 #
b1000010 (
b101010 !
b101010 '
b101010 ,
b110 -
1$
#80000
0$
#85000
b11111111111111111111111111111111 )
b1001001 #
b1001001 (
b110001 !
b110001 '
b110001 ,
b111 -
1$
#90000
0$
#95000
b11111111111111111111111111111111 )
b1010110 #
b1010110 (
b111000 !
b111000 '
b111000 ,
b1000 -
1$
#100000
0$
#105000
b11111111111111111111111111111111 )
b1100011 #
b1100011 (
b111111 !
b111111 '
b111111 ,
b1001 -
1$
#110000
0$
#115000
b11111111111111111111111111111111 )
b1110000 #
b1110000 (
b1000110 !
b1000110 '
b1000110 ,
b1010 -
1$
#120000
0$
#125000
1"
1$
